aiogram_input/__init__.py
aiogram_input/core.py
aiogram_input/middleware.py
aiogram_input/router.py
aiogram_input/session.py
aiogram_input/storage.py
aiogram_input/types.py
aiogram_input-3.1.0.dist-info/licenses/LICENSE
aiogram_input-3.1.0.dist-info/METADATA
aiogram_input-3.1.0.dist-info/WHEEL
aiogram_input-3.1.0.dist-info/top_level.txt
aiogram_input-3.1.0.dist-info/RECORD
