Metadata-Version: 2.4
Name: aiogram_input
Version: 3.1.0
Summary: A modular, multi-client library for aiogram to handle user response waiting in Telegram bots.
Home-page: https://github.com/mamahoos/aiogram-input
Author: mamahoos
Author-email: m4m4hoos@example.com
Classifier: Programming Language :: Python :: 3
Classifier: License :: OSI Approved :: MIT License
Classifier: Operating System :: OS Independent
Requires-Python: >=3.8
License-File: LICENSE
Requires-Dist: aiogram>=3.0.0
Dynamic: author
Dynamic: author-email
Dynamic: classifier
Dynamic: description
Dynamic: description-content-type
Dynamic: home-page
Dynamic: license-file
Dynamic: requires-dist
Dynamic: requires-python
Dynamic: summary
